nescient/__main__.py
nescient/__init__.py
nescient/packer.py
nescient/nessie.png
nescient/gui.py
nescient/process.py
nescient/timing.py
nescient/test.py
nescient/nessie.ico
nescient/crypto/tools.py
nescient/crypto/aes.pyx
nescient/crypto/chacha.cpython-36m-i386-linux-gnu.so
nescient/crypto/aes.cpython-36m-i386-linux-gnu.so
nescient/crypto/__init__.py
nescient/crypto/chacha.pyx
nescient/crypto/galois.py
nescient/crypto/chacha.pxd
nescient/.libs/libgomp-c0bd41c1.so.1.0.0
nescient/resources/banner.py
nescient/resources/__init__.py
nescient/resources/nessie.gif
nescient/resources/banner.gif
nescient/resources/nessie.py
nescient/resources/nessie_lock.py
nescient/resources/nessie_lock.gif
Nescient-0.9.0.dist-info/WHEEL
Nescient-0.9.0.dist-info/top_level.txt
Nescient-0.9.0.dist-info/METADATA
Nescient-0.9.0.dist-info/RECORD
Nescient-0.9.0.dist-info/entry_points.txt
