Metadata-Version: 2.1
Name: Nescient
Version: 0.9.0
Summary: Store, encrypt and decrypt files to and from encrypted, authenticated containers.
Home-page: https://github.com/arantonitis/nescient
Author: Ariel Antonitis
Author-email: arant@mit.edu
License: MIT
Platform: UNKNOWN
Classifier: License :: OSI Approved :: MIT License
Classifier: Development Status :: 4 - Beta
Classifier: Topic :: Security :: Cryptography
Classifier: Programming Language :: Python :: 3.5
Classifier: Programming Language :: Python :: 3.6
Requires-Python: >=3.5
